<?xml version="1.0" encoding="utf-8" ?>
<updates>
  <update version="1.1.6">
    <files>
      <file path="Components/LiveSplit.OriAndTheBlindForest.dll" status="changed"/>
    </files>
    <changelog>
      <change>
        Merged changes by Quentillionaire to make the checkboxes in the settings make more sense.
      </change>
    </changelog>
  </update>
  <update version="1.1.5">
    <files>
      <file path="Components/LiveSplit.OriAndTheBlindForest.dll" status="changed"/>
    </files>
    <changelog>
      <change>
        Updated the autosplitter to support LiveSplit 1.6.
      </change>
    </changelog>
  </update>
  <update version="1.1.4">
    <files>
      <file path="Components/LiveSplit.OriAndTheBlindForest.dll" status="changed"/>
    </files>
    <changelog>
      <change>
        Added checkbox to include splits that don't actually split.
      </change>
      <change>
        Added an "In Game" split to split when reentering the game. Combined with the above, a skill such as "Wall Jump" can be marked "Don't Split" followed by an "In Game" split to split when you re-enter the game after getting an ability rather than splitting immediately on pickup.
      </change>
      <change>
        Updated the default splits for all categories to reflect route changes.
      </change>
      <change>
        Added new All Skills category along with default splits.
      </change>
      <change>
        Added Map% display for 100% runs.
      </change>
    </changelog>
  </update>
  <update version="1.1.3">
    <files>
      <file path="Components/LiveSplit.OriAndTheBlindForest.dll" status="changed"/>
    </files>
    <changelog>
      <change>
        Changed the default `Iceless` split to be higher to avoid false splits. 
        You will need to manually update your splits changing them from `Iceless` to something else and then back to `Iceless` to effect this change.
      </change>
    </changelog>
  </update>
  <update version="1.1.2">
    <files>
      <file path="Components/LiveSplit.OriAndTheBlindForest.dll" status="changed"/>
    </files>
    <changelog>
      <change>
        Added support for LiveSplit updates.
      </change>
    </changelog>
  </update>
  <update version="1.1.1">
    <files>
      <file path="Components/LiveSplit.OriAndTheBlindForest.dll" status="changed"/>
    </files>
    <changelog>
      <change>
        Ignore skip split commands from LiveSplit. Previously it tried to advance its internal 
        state to allow skipping buggy splits, however, due to stability this now is 
        often the wrong behavior.
      </change>
    </changelog>
  </update>
</updates>